pygments_q/__init__.py
pygments_q/filters/__init__.py
pygments_q/formatters/__init__.py
pygments_q/formatters/pytest.py
pygments_q/lexers/__init__.py
pygments_q/lexers/q.py
pygments_q-0.5.dist-info/DESCRIPTION.rst
pygments_q-0.5.dist-info/entry_points.txt
pygments_q-0.5.dist-info/METADATA
pygments_q-0.5.dist-info/metadata.json
pygments_q-0.5.dist-info/RECORD
pygments_q-0.5.dist-info/top_level.txt
pygments_q-0.5.dist-info/WHEEL
pygments_q-0.5.dist-info/zip-safe
