Metadata-Version: 2.0
Name: pygments-q
Version: 0.5
Summary: Pygments lexer for the Q language
Home-page: http://pyq.enlnt.com/pygments-q
Author: Enlightenment Research, LLC
Author-email: pyq@enlnt.com
License: BSD
Keywords: pygments pyq q k kx kdb+
Platform: UNKNOWN
Classifier: Development Status :: 3 - Alpha
Classifier: Environment :: Plugins
Classifier: Intended Audience :: Developers
Classifier: License :: OSI Approved :: BSD License
Classifier: Operating System :: OS Independent
Classifier: Programming Language :: Python :: 2
Classifier: Programming Language :: Python :: 3
Requires-Dist: pygments (>=2.0)
